{
	"fps": 24,
	"hierarchy": [
		{
			"name": "null",
			"parent": "-1"
		},
		{
			"name": "cam_watch_bake",
			"parent": "0"
		}
	],
	"frames": [
		{
			"position": [0.0, 0.0, -0.0, -3.3519, 0.7752, -0.1967],
			"quaternion": [0.0, 0.0, -0.0, 1.0, -0.0777, -0.7228, -0.0824, 0.6817],
			"scale": [1.0, 1.0, 1.0, 1.0, 1.0, 1.0]
		},
		{
			"position": [0.0, 0.0, -0.0, -3.3606, 0.7608, -0.0501],
			"quaternion": [0.0, 0.0, -0.0, 1.0, -0.078, -0.7079, -0.0791, 0.6975],
			"scale": [1.0, 1.0, 1.0, 1.0, 1.0, 1.0]
		},
		{
			"position": [0.0, 0.0, -0.0, -3.3628, 0.7465, 0.0969],
			"quaternion": [0.0, 0.0, -0.0, 1.0, -0.0781, -0.6927, -0.0759, 0.7129],
			"scale": [1.0, 1.0, 1.0, 1.0, 1.0, 1.0]
		},
		{
			"position": [0.0, 0.0, -0.0, -3.3585, 0.7323, 0.244],
			"quaternion": [0.0, 0.0, -0.0, 1.0, -0.0783, -0.6771, -0.0728, 0.7281],
			"scale": [1.0, 1.0, 1.0, 1.0, 1.0, 1.0]
		},
		{
			"position": [0.0, 0.0, -0.0, -3.3476, 0.7181, 0.3908],
			"quaternion": [0.0, 0.0, -0.0, 1.0, -0.0783, -0.6612, -0.0697, 0.7429],
			"scale": [1.0, 1.0, 1.0, 1.0, 1.0, 1.0]
		},
		{
			"position": [0.0, 0.0, -0.0, -3.3303, 0.7041, 0.5372],
			"quaternion": [0.0, 0.0, -0.0, 1.0, -0.0782, -0.6449, -0.0666, 0.7573],
			"scale": [1.0, 1.0, 1.0, 1.0, 1.0, 1.0]
		},
		{
			"position": [0.0, 0.0, -0.0, -3.3064, 0.6901, 0.6828],
			"quaternion": [0.0, 0.0, -0.0, 1.0, -0.078, -0.6284, -0.0636, 0.7714],
			"scale": [1.0, 1.0, 1.0, 1.0, 1.0, 1.0]
		},
		{
			"position": [0.0, 0.0, -0.0, -3.2762, 0.6762, 0.8273],
			"quaternion": [0.0, 0.0, -0.0, 1.0, -0.0778, -0.6115, -0.0606, 0.7851],
			"scale": [1.0, 1.0, 1.0, 1.0, 1.0, 1.0]
		},
		{
			"position": [0.0, 0.0, -0.0, -3.2395, 0.6624, 0.9705],
			"quaternion": [0.0, 0.0, -0.0, 1.0, -0.0775, -0.5943, -0.0577, 0.7984],
			"scale": [1.0, 1.0, 1.0, 1.0, 1.0, 1.0]
		},
		{
			"position": [0.0, 0.0, -0.0, -3.1965, 0.6486, 1.112],
			"quaternion": [0.0, 0.0, -0.0, 1.0, -0.0771, -0.5768, -0.0548, 0.8114],
			"scale": [1.0, 1.0, 1.0, 1.0, 1.0, 1.0]
		},
		{
			"position": [0.0, 0.0, -0.0, -3.1473, 0.635, 1.2516],
			"quaternion": [0.0, 0.0, -0.0, 1.0, -0.0766, -0.5591, -0.052, 0.824],
			"scale": [1.0, 1.0, 1.0, 1.0, 1.0, 1.0]
		},
		{
			"position": [0.0, 0.0, -0.0, -3.0919, 0.6214, 1.389],
			"quaternion": [0.0, 0.0, -0.0, 1.0, -0.076, -0.541, -0.0492, 0.8361],
			"scale": [1.0, 1.0, 1.0, 1.0, 1.0, 1.0]
		},
		{
			"position": [0.0, 0.0, -0.0, -3.0304, 0.6079, 1.5238],
			"quaternion": [0.0, 0.0, -0.0, 1.0, -0.0754, -0.5227, -0.0465, 0.8479],
			"scale": [1.0, 1.0, 1.0, 1.0, 1.0, 1.0]
		},
		{
			"position": [0.0, 0.0, -0.0, -2.963, 0.5945, 1.656],
			"quaternion": [0.0, 0.0, -0.0, 1.0, -0.0747, -0.5041, -0.0438, 0.8593],
			"scale": [1.0, 1.0, 1.0, 1.0, 1.0, 1.0]
		},
		{
			"position": [0.0, 0.0, -0.0, -2.8898, 0.5811, 1.7851],
			"quaternion": [0.0, 0.0, -0.0, 1.0, -0.0739, -0.4853, -0.0412, 0.8702],
			"scale": [1.0, 1.0, 1.0, 1.0, 1.0, 1.0]
		},
		{
			"position": [0.0, 0.0, -0.0, -2.8109, 0.5678, 1.9109],
			"quaternion": [0.0, 0.0, -0.0, 1.0, -0.0731, -0.4663, -0.0387, 0.8808],
			"scale": [1.0, 1.0, 1.0, 1.0, 1.0, 1.0]
		},
		{
			"position": [0.0, 0.0, -0.0, -2.7264, 0.5546, 2.0332],
			"quaternion": [0.0, 0.0, -0.0, 1.0, -0.0722, -0.447, -0.0362, 0.8909],
			"scale": [1.0, 1.0, 1.0, 1.0, 1.0, 1.0]
		},
		{
			"position": [0.0, 0.0, -0.0, -2.6366, 0.5415, 2.1517],
			"quaternion": [0.0, 0.0, -0.0, 1.0, -0.0712, -0.4275, -0.0338, 0.9006],
			"scale": [1.0, 1.0, 1.0, 1.0, 1.0, 1.0]
		},
		{
			"position": [0.0, 0.0, -0.0, -2.5416, 0.5285, 2.2663],
			"quaternion": [0.0, 0.0, -0.0, 1.0, -0.0702, -0.4077, -0.0315, 0.9099],
			"scale": [1.0, 1.0, 1.0, 1.0, 1.0, 1.0]
		},
		{
			"position": [0.0, 0.0, -0.0, -2.4416, 0.5155, 2.3766],
			"quaternion": [0.0, 0.0, -0.0, 1.0, -0.0691, -0.3878, -0.0292, 0.9187],
			"scale": [1.0, 1.0, 1.0, 1.0, 1.0, 1.0]
		},
		{
			"position": [0.0, 0.0, -0.0, -2.3367, 0.5026, 2.4824],
			"quaternion": [0.0, 0.0, -0.0, 1.0, -0.068, -0.3677, -0.027, 0.9271],
			"scale": [1.0, 1.0, 1.0, 1.0, 1.0, 1.0]
		},
		{
			"position": [0.0, 0.0, -0.0, -2.2272, 0.4898, 2.5835],
			"quaternion": [0.0, 0.0, -0.0, 1.0, -0.0668, -0.3474, -0.0248, 0.935],
			"scale": [1.0, 1.0, 1.0, 1.0, 1.0, 1.0]
		},
		{
			"position": [0.0, 0.0, -0.0, -2.1133, 0.477, 2.6798],
			"quaternion": [0.0, 0.0, -0.0, 1.0, -0.0655, -0.3269, -0.0227, 0.9425],
			"scale": [1.0, 1.0, 1.0, 1.0, 1.0, 1.0]
		},
		{
			"position": [0.0, 0.0, -0.0, -1.9952, 0.4643, 2.771],
			"quaternion": [0.0, 0.0, -0.0, 1.0, -0.0643, -0.3063, -0.0207, 0.9495],
			"scale": [1.0, 1.0, 1.0, 1.0, 1.0, 1.0]
		},
		{
			"position": [0.0, 0.0, -0.0, -1.8732, 0.4517, 2.857],
			"quaternion": [0.0, 0.0, -0.0, 1.0, -0.0629, -0.2855, -0.0188, 0.9561],
			"scale": [1.0, 1.0, 1.0, 1.0, 1.0, 1.0]
		},
		{
			"position": [0.0, 0.0, -0.0, -1.7474, 0.4391, 2.9375],
			"quaternion": [0.0, 0.0, -0.0, 1.0, -0.0616, -0.2646, -0.0169, 0.9623],
			"scale": [1.0, 1.0, 1.0, 1.0, 1.0, 1.0]
		},
		{
			"position": [0.0, 0.0, -0.0, -1.6181, 0.4267, 3.0124],
			"quaternion": [0.0, 0.0, -0.0, 1.0, -0.0602, -0.2435, -0.0151, 0.9679],
			"scale": [1.0, 1.0, 1.0, 1.0, 1.0, 1.0]
		},
		{
			"position": [0.0, 0.0, -0.0, -1.4856, 0.4142, 3.0816],
			"quaternion": [0.0, 0.0, -0.0, 1.0, -0.0587, -0.2223, -0.0134, 0.9731],
			"scale": [1.0, 1.0, 1.0, 1.0, 1.0, 1.0]
		},
		{
			"position": [0.0, 0.0, -0.0, -1.3501, 0.4019, 3.145],
			"quaternion": [0.0, 0.0, -0.0, 1.0, -0.0572, -0.201, -0.0118, 0.9778],
			"scale": [1.0, 1.0, 1.0, 1.0, 1.0, 1.0]
		},
		{
			"position": [0.0, 0.0, -0.0, -1.2118, 0.3896, 3.2023],
			"quaternion": [0.0, 0.0, -0.0, 1.0, -0.0557, -0.1796, -0.0102, 0.9821],
			"scale": [1.0, 1.0, 1.0, 1.0, 1.0, 1.0]
		},
		{
			"position": [0.0, 0.0, -0.0, -1.0712, 0.3774, 3.2535],
			"quaternion": [0.0, 0.0, -0.0, 1.0, -0.0542, -0.1581, -0.0087, 0.9859],
			"scale": [1.0, 1.0, 1.0, 1.0, 1.0, 1.0]
		},
		{
			"position": [0.0, 0.0, -0.0, -0.9283, 0.3653, 3.2984],
			"quaternion": [0.0, 0.0, -0.0, 1.0, -0.0526, -0.1366, -0.0073, 0.9892],
			"scale": [1.0, 1.0, 1.0, 1.0, 1.0, 1.0]
		},
		{
			"position": [0.0, 0.0, -0.0, -0.7836, 0.3532, 3.3371],
			"quaternion": [0.0, 0.0, -0.0, 1.0, -0.051, -0.1149, -0.0059, 0.992],
			"scale": [1.0, 1.0, 1.0, 1.0, 1.0, 1.0]
		},
		{
			"position": [0.0, 0.0, -0.0, -0.6373, 0.3412, 3.3693],
			"quaternion": [0.0, 0.0, -0.0, 1.0, -0.0493, -0.0932, -0.0046, 0.9944],
			"scale": [1.0, 1.0, 1.0, 1.0, 1.0, 1.0]
		},
		{
			"position": [0.0, 0.0, -0.0, -0.4896, 0.3292, 3.3951],
			"quaternion": [0.0, 0.0, -0.0, 1.0, -0.0477, -0.0715, -0.0034, 0.9963],
			"scale": [1.0, 1.0, 1.0, 1.0, 1.0, 1.0]
		},
		{
			"position": [0.0, 0.0, -0.0, -0.3409, 0.3173, 3.4144],
			"quaternion": [0.0, 0.0, -0.0, 1.0, -0.046, -0.0497, -0.0023, 0.9977],
			"scale": [1.0, 1.0, 1.0, 1.0, 1.0, 1.0]
		},
		{
			"position": [0.0, 0.0, -0.0, -0.1914, 0.3055, 3.4271],
			"quaternion": [0.0, 0.0, -0.0, 1.0, -0.0443, -0.0279, -0.0012, 0.9986],
			"scale": [1.0, 1.0, 1.0, 1.0, 1.0, 1.0]
		},
		{
			"position": [0.0, 0.0, -0.0, -0.0415, 0.2937, 3.4332],
			"quaternion": [0.0, 0.0, -0.0, 1.0, -0.0426, -0.006, -0.0003, 0.9991],
			"scale": [1.0, 1.0, 1.0, 1.0, 1.0, 1.0]
		},
		{
			"position": [0.0, 0.0, -0.0, 0.1086, 0.282, 3.4327],
			"quaternion": [0.0, 0.0, -0.0, 1.0, -0.0409, 0.0158, 0.0006, 0.999],
			"scale": [1.0, 1.0, 1.0, 1.0, 1.0, 1.0]
		},
		{
			"position": [0.0, 0.0, -0.0, 0.2586, 0.2703, 3.4256],
			"quaternion": [0.0, 0.0, -0.0, 1.0, -0.0392, 0.0376, 0.0015, 0.9985],
			"scale": [1.0, 1.0, 1.0, 1.0, 1.0, 1.0]
		},
		{
			"position": [0.0, 0.0, -0.0, 0.4081, 0.2587, 3.412],
			"quaternion": [0.0, 0.0, -0.0, 1.0, -0.0375, 0.0595, 0.0022, 0.9975],
			"scale": [1.0, 1.0, 1.0, 1.0, 1.0, 1.0]
		},
		{
			"position": [0.0, 0.0, -0.0, 0.557, 0.2472, 3.3917],
			"quaternion": [0.0, 0.0, -0.0, 1.0, -0.0358, 0.0812, 0.0029, 0.996],
			"scale": [1.0, 1.0, 1.0, 1.0, 1.0, 1.0]
		},
		{
			"position": [0.0, 0.0, -0.0, 0.7048, 0.2357, 3.3649],
			"quaternion": [0.0, 0.0, -0.0, 1.0, -0.034, 0.103, 0.0035, 0.9941],
			"scale": [1.0, 1.0, 1.0, 1.0, 1.0, 1.0]
		},
		{
			"position": [0.0, 0.0, -0.0, 0.8514, 0.2242, 3.3316],
			"quaternion": [0.0, 0.0, -0.0, 1.0, -0.0323, 0.1247, 0.0041, 0.9917],
			"scale": [1.0, 1.0, 1.0, 1.0, 1.0, 1.0]
		},
		{
			"position": [0.0, 0.0, -0.0, 0.9964, 0.2129, 3.2919],
			"quaternion": [0.0, 0.0, -0.0, 1.0, -0.0306, 0.1464, 0.0045, 0.9887],
			"scale": [1.0, 1.0, 1.0, 1.0, 1.0, 1.0]
		},
		{
			"position": [0.0, 0.0, -0.0, 1.1395, 0.2015, 3.2459],
			"quaternion": [0.0, 0.0, -0.0, 1.0, -0.0288, 0.1679, 0.0049, 0.9854],
			"scale": [1.0, 1.0, 1.0, 1.0, 1.0, 1.0]
		},
		{
			"position": [0.0, 0.0, -0.0, 1.2805, 0.1903, 3.1936],
			"quaternion": [0.0, 0.0, -0.0, 1.0, -0.0271, 0.1894, 0.0052, 0.9815],
			"scale": [1.0, 1.0, 1.0, 1.0, 1.0, 1.0]
		},
		{
			"position": [0.0, 0.0, -0.0, 1.4191, 0.179, 3.1352],
			"quaternion": [0.0, 0.0, -0.0, 1.0, -0.0254, 0.2109, 0.0055, 0.9772],
			"scale": [1.0, 1.0, 1.0, 1.0, 1.0, 1.0]
		},
		{
			"position": [0.0, 0.0, -0.0, 1.555, 0.1679, 3.0707],
			"quaternion": [0.0, 0.0, -0.0, 1.0, -0.0237, 0.2322, 0.0057, 0.9724],
			"scale": [1.0, 1.0, 1.0, 1.0, 1.0, 1.0]
		},
		{
			"position": [0.0, 0.0, -0.0, 1.6879, 0.1567, 3.0002],
			"quaternion": [0.0, 0.0, -0.0, 1.0, -0.022, 0.2534, 0.0058, 0.9671],
			"scale": [1.0, 1.0, 1.0, 1.0, 1.0, 1.0]
		},
		{
			"position": [0.0, 0.0, -0.0, 1.8177, 0.1457, 2.924],
			"quaternion": [0.0, 0.0, -0.0, 1.0, -0.0203, 0.2745, 0.0058, 0.9614],
			"scale": [1.0, 1.0, 1.0, 1.0, 1.0, 1.0]
		},
		{
			"position": [0.0, 0.0, -0.0, 1.944, 0.1346, 2.8422],
			"quaternion": [0.0, 0.0, -0.0, 1.0, -0.0187, 0.2954, 0.0058, 0.9552],
			"scale": [1.0, 1.0, 1.0, 1.0, 1.0, 1.0]
		},
		{
			"position": [0.0, 0.0, -0.0, 2.0665, 0.1237, 2.7548],
			"quaternion": [0.0, 0.0, -0.0, 1.0, -0.017, 0.3162, 0.0057, 0.9485],
			"scale": [1.0, 1.0, 1.0, 1.0, 1.0, 1.0]
		},
		{
			"position": [0.0, 0.0, -0.0, 2.1852, 0.1127, 2.6622],
			"quaternion": [0.0, 0.0, -0.0, 1.0, -0.0154, 0.3369, 0.0055, 0.9414],
			"scale": [1.0, 1.0, 1.0, 1.0, 1.0, 1.0]
		},
		{
			"position": [0.0, 0.0, -0.0, 2.2997, 0.1019, 2.5644],
			"quaternion": [0.0, 0.0, -0.0, 1.0, -0.0138, 0.3574, 0.0053, 0.9338],
			"scale": [1.0, 1.0, 1.0, 1.0, 1.0, 1.0]
		},
		{
			"position": [0.0, 0.0, -0.0, 2.4097, 0.091, 2.4617],
			"quaternion": [0.0, 0.0, -0.0, 1.0, -0.0122, 0.3777, 0.005, 0.9258],
			"scale": [1.0, 1.0, 1.0, 1.0, 1.0, 1.0]
		},
		{
			"position": [0.0, 0.0, -0.0, 2.5152, 0.0802, 2.3542],
			"quaternion": [0.0, 0.0, -0.0, 1.0, -0.0107, 0.3979, 0.0046, 0.9174],
			"scale": [1.0, 1.0, 1.0, 1.0, 1.0, 1.0]
		},
		{
			"position": [0.0, 0.0, -0.0, 2.6158, 0.0695, 2.2422],
			"quaternion": [0.0, 0.0, -0.0, 1.0, -0.0092, 0.4178, 0.0042, 0.9085],
			"scale": [1.0, 1.0, 1.0, 1.0, 1.0, 1.0]
		},
		{
			"position": [0.0, 0.0, -0.0, 2.7115, 0.0588, 2.1259],
			"quaternion": [0.0, 0.0, -0.0, 1.0, -0.0077, 0.4376, 0.0037, 0.8991],
			"scale": [1.0, 1.0, 1.0, 1.0, 1.0, 1.0]
		},
		{
			"position": [0.0, 0.0, -0.0, 2.8019, 0.0481, 2.0055],
			"quaternion": [0.0, 0.0, -0.0, 1.0, -0.0062, 0.4571, 0.0032, 0.8894],
			"scale": [1.0, 1.0, 1.0, 1.0, 1.0, 1.0]
		},
		{
			"position": [0.0, 0.0, -0.0, 2.887, 0.0375, 1.8812],
			"quaternion": [0.0, 0.0, -0.0, 1.0, -0.0048, 0.4765, 0.0026, 0.8792],
			"scale": [1.0, 1.0, 1.0, 1.0, 1.0, 1.0]
		},
		{
			"position": [0.0, 0.0, -0.0, 2.9665, 0.0269, 1.7533],
			"quaternion": [0.0, 0.0, -0.0, 1.0, -0.0034, 0.4956, 0.0019, 0.8686],
			"scale": [1.0, 1.0, 1.0, 1.0, 1.0, 1.0]
		},
		{
			"position": [0.0, 0.0, -0.0, 3.0404, 0.0163, 1.622],
			"quaternion": [0.0, 0.0, -0.0, 1.0, -0.002, 0.5144, 0.0012, 0.8575],
			"scale": [1.0, 1.0, 1.0, 1.0, 1.0, 1.0]
		},
		{
			"position": [0.0, 0.0, -0.0, 3.1084, 0.0058, 1.4876],
			"quaternion": [0.0, 0.0, -0.0, 1.0, -0.0007, 0.5331, 0.0005, 0.8461],
			"scale": [1.0, 1.0, 1.0, 1.0, 1.0, 1.0]
		},
		{
			"position": [0.0, 0.0, -0.0, 3.1704, -0.0047, 1.3504],
			"quaternion": [0.0, 0.0, -0.0, 1.0, 0.0006, 0.5514, -0.0004, 0.8342],
			"scale": [1.0, 1.0, 1.0, 1.0, 1.0, 1.0]
		},
		{
			"position": [0.0, 0.0, -0.0, 3.2264, -0.0151, 1.2105],
			"quaternion": [0.0, 0.0, -0.0, 1.0, 0.0018, 0.5695, -0.0012, 0.822],
			"scale": [1.0, 1.0, 1.0, 1.0, 1.0, 1.0]
		},
		{
			"position": [0.0, 0.0, -0.0, 3.2761, -0.0255, 1.0684],
			"quaternion": [0.0, 0.0, -0.0, 1.0, 0.003, 0.5873, -0.0022, 0.8093],
			"scale": [1.0, 1.0, 1.0, 1.0, 1.0, 1.0]
		},
		{
			"position": [0.0, 0.0, -0.0, 3.3196, -0.0359, 0.9242],
			"quaternion": [0.0, 0.0, -0.0, 1.0, 0.0041, 0.6049, -0.0031, 0.7963],
			"scale": [1.0, 1.0, 1.0, 1.0, 1.0, 1.0]
		},
		{
			"position": [0.0, 0.0, -0.0, 3.3567, -0.0462, 0.7782],
			"quaternion": [0.0, 0.0, -0.0, 1.0, 0.0052, 0.6221, -0.0042, 0.7829],
			"scale": [1.0, 1.0, 1.0, 1.0, 1.0, 1.0]
		},
		{
			"position": [0.0, 0.0, -0.0, 3.3873, -0.0565, 0.6307],
			"quaternion": [0.0, 0.0, -0.0, 1.0, 0.0063, 0.6391, -0.0052, 0.7691],
			"scale": [1.0, 1.0, 1.0, 1.0, 1.0, 1.0]
		},
		{
			"position": [0.0, 0.0, -0.0, 3.4115, -0.0668, 0.4821],
			"quaternion": [0.0, 0.0, -0.0, 1.0, 0.0073, 0.6557, -0.0064, 0.7549],
			"scale": [1.0, 1.0, 1.0, 1.0, 1.0, 1.0]
		},
		{
			"position": [0.0, 0.0, -0.0, 3.4291, -0.077, 0.3325],
			"quaternion": [0.0, 0.0, -0.0, 1.0, 0.0083, 0.6721, -0.0075, 0.7404],
			"scale": [1.0, 1.0, 1.0, 1.0, 1.0, 1.0]
		},
		{
			"position": [0.0, 0.0, -0.0, 3.4401, -0.0872, 0.1824],
			"quaternion": [0.0, 0.0, -0.0, 1.0, 0.0092, 0.6881, -0.0087, 0.7255],
			"scale": [1.0, 1.0, 1.0, 1.0, 1.0, 1.0]
		},
		{
			"position": [0.0, 0.0, -0.0, 3.4445, -0.0974, 0.0319],
			"quaternion": [0.0, 0.0, -0.0, 1.0, 0.01, 0.7038, -0.01, 0.7103],
			"scale": [1.0, 1.0, 1.0, 1.0, 1.0, 1.0]
		},
		{
			"position": [0.0, 0.0, -0.0, 3.4423, -0.1076, -0.1187],
			"quaternion": [0.0, 0.0, -0.0, 1.0, 0.0108, 0.7191, -0.0112, 0.6947],
			"scale": [1.0, 1.0, 1.0, 1.0, 1.0, 1.0]
		},
		{
			"position": [0.0, 0.0, -0.0, 3.4335, -0.1177, -0.269],
			"quaternion": [0.0, 0.0, -0.0, 1.0, 0.0116, 0.7341, -0.0125, 0.6788],
			"scale": [1.0, 1.0, 1.0, 1.0, 1.0, 1.0]
		},
		{
			"position": [0.0, 0.0, -0.0, 3.4181, -0.1278, -0.4187],
			"quaternion": [0.0, 0.0, -0.0, 1.0, 0.0123, 0.7487, -0.0139, 0.6626],
			"scale": [1.0, 1.0, 1.0, 1.0, 1.0, 1.0]
		},
		{
			"position": [0.0, 0.0, -0.0, 3.3961, -0.1379, -0.5676],
			"quaternion": [0.0, 0.0, -0.0, 1.0, 0.0129, 0.763, -0.0153, 0.6461],
			"scale": [1.0, 1.0, 1.0, 1.0, 1.0, 1.0]
		},
		{
			"position": [0.0, 0.0, -0.0, 3.3677, -0.148, -0.7154],
			"quaternion": [0.0, 0.0, -0.0, 1.0, 0.0135, 0.7769, -0.0167, 0.6292],
			"scale": [1.0, 1.0, 1.0, 1.0, 1.0, 1.0]
		},
		{
			"position": [0.0, 0.0, -0.0, 3.3328, -0.158, -0.8617],
			"quaternion": [0.0, 0.0, -0.0, 1.0, 0.014, 0.7905, -0.0181, 0.6121],
			"scale": [1.0, 1.0, 1.0, 1.0, 1.0, 1.0]
		},
		{
			"position": [0.0, 0.0, -0.0, 3.2915, -0.168, -1.0064],
			"quaternion": [0.0, 0.0, -0.0, 1.0, 0.0145, 0.8036, -0.0196, 0.5946],
			"scale": [1.0, 1.0, 1.0, 1.0, 1.0, 1.0]
		},
		{
			"position": [0.0, 0.0, -0.0, 3.2439, -0.178, -1.1491],
			"quaternion": [0.0, 0.0, -0.0, 1.0, 0.0149, 0.8164, -0.0211, 0.5769],
			"scale": [1.0, 1.0, 1.0, 1.0, 1.0, 1.0]
		},
		{
			"position": [0.0, 0.0, -0.0, 3.1901, -0.188, -1.2896],
			"quaternion": [0.0, 0.0, -0.0, 1.0, 0.0153, 0.8288, -0.0226, 0.5589],
			"scale": [1.0, 1.0, 1.0, 1.0, 1.0, 1.0]
		},
		{
			"position": [0.0, 0.0, -0.0, 3.1302, -0.1979, -1.4275],
			"quaternion": [0.0, 0.0, -0.0, 1.0, 0.0155, 0.8408, -0.0242, 0.5406],
			"scale": [1.0, 1.0, 1.0, 1.0, 1.0, 1.0]
		},
		{
			"position": [0.0, 0.0, -0.0, 3.0643, -0.2079, -1.5627],
			"quaternion": [0.0, 0.0, -0.0, 1.0, 0.0158, 0.8523, -0.0257, 0.5221],
			"scale": [1.0, 1.0, 1.0, 1.0, 1.0, 1.0]
		},
		{
			"position": [0.0, 0.0, -0.0, 2.9925, -0.2178, -1.6948],
			"quaternion": [0.0, 0.0, -0.0, 1.0, 0.0159, 0.8635, -0.0273, 0.5033],
			"scale": [1.0, 1.0, 1.0, 1.0, 1.0, 1.0]
		},
		{
			"position": [0.0, 0.0, -0.0, 2.9151, -0.2277, -1.8236],
			"quaternion": [0.0, 0.0, -0.0, 1.0, 0.016, 0.8743, -0.0289, 0.4843],
			"scale": [1.0, 1.0, 1.0, 1.0, 1.0, 1.0]
		},
		{
			"position": [0.0, 0.0, -0.0, 2.8321, -0.2376, -1.9488],
			"quaternion": [0.0, 0.0, -0.0, 1.0, 0.0161, 0.8846, -0.0305, 0.4651],
			"scale": [1.0, 1.0, 1.0, 1.0, 1.0, 1.0]
		},
		{
			"position": [0.0, 0.0, -0.0, 2.7436, -0.2474, -2.0703],
			"quaternion": [0.0, 0.0, -0.0, 1.0, 0.016, 0.8945, -0.0322, 0.4456],
			"scale": [1.0, 1.0, 1.0, 1.0, 1.0, 1.0]
		},
		{
			"position": [0.0, 0.0, -0.0, 2.65, -0.2573, -2.1878],
			"quaternion": [0.0, 0.0, -0.0, 1.0, 0.0159, 0.904, -0.0338, 0.4259],
			"scale": [1.0, 1.0, 1.0, 1.0, 1.0, 1.0]
		},
		{
			"position": [0.0, 0.0, -0.0, 2.5513, -0.2671, -2.301],
			"quaternion": [0.0, 0.0, -0.0, 1.0, 0.0158, 0.913, -0.0354, 0.4061],
			"scale": [1.0, 1.0, 1.0, 1.0, 1.0, 1.0]
		},
		{
			"position": [0.0, 0.0, -0.0, 2.4478, -0.277, -2.4097],
			"quaternion": [0.0, 0.0, -0.0, 1.0, 0.0155, 0.9216, -0.0371, 0.386],
			"scale": [1.0, 1.0, 1.0, 1.0, 1.0, 1.0]
		},
		{
			"position": [0.0, 0.0, -0.0, 2.3396, -0.2868, -2.5138],
			"quaternion": [0.0, 0.0, -0.0, 1.0, 0.0152, 0.9298, -0.0388, 0.3657],
			"scale": [1.0, 1.0, 1.0, 1.0, 1.0, 1.0]
		},
		{
			"position": [0.0, 0.0, -0.0, 2.227, -0.2966, -2.613],
			"quaternion": [0.0, 0.0, -0.0, 1.0, 0.0149, 0.9375, -0.0404, 0.3453],
			"scale": [1.0, 1.0, 1.0, 1.0, 1.0, 1.0]
		},
		{
			"position": [0.0, 0.0, -0.0, 2.1101, -0.3064, -2.7071],
			"quaternion": [0.0, 0.0, -0.0, 1.0, 0.0145, 0.9448, -0.0421, 0.3247],
			"scale": [1.0, 1.0, 1.0, 1.0, 1.0, 1.0]
		},
		{
			"position": [0.0, 0.0, -0.0, 1.9893, -0.3162, -2.796],
			"quaternion": [0.0, 0.0, -0.0, 1.0, 0.014, 0.9516, -0.0438, 0.304],
			"scale": [1.0, 1.0, 1.0, 1.0, 1.0, 1.0]
		},
		{
			"position": [0.0, 0.0, -0.0, 1.8647, -0.326, -2.8795],
			"quaternion": [0.0, 0.0, -0.0, 1.0, 0.0134, 0.9579, -0.0454, 0.2831],
			"scale": [1.0, 1.0, 1.0, 1.0, 1.0, 1.0]
		},
		{
			"position": [0.0, 0.0, -0.0, 1.7366, -0.3358, -2.9574],
			"quaternion": [0.0, 0.0, -0.0, 1.0, 0.0128, 0.9638, -0.0471, 0.2621],
			"scale": [1.0, 1.0, 1.0, 1.0, 1.0, 1.0]
		},
		{
			"position": [0.0, 0.0, -0.0, 1.6053, -0.3455, -3.0296],
			"quaternion": [0.0, 0.0, -0.0, 1.0, 0.0121, 0.9692, -0.0487, 0.2409],
			"scale": [1.0, 1.0, 1.0, 1.0, 1.0, 1.0]
		},
		{
			"position": [0.0, 0.0, -0.0, 1.4709, -0.3553, -3.096],
			"quaternion": [0.0, 0.0, -0.0, 1.0, 0.0114, 0.9742, -0.0504, 0.2197],
			"scale": [1.0, 1.0, 1.0, 1.0, 1.0, 1.0]
		},
		{
			"position": [0.0, 0.0, -0.0, 1.3338, -0.3651, -3.1564],
			"quaternion": [0.0, 0.0, -0.0, 1.0, 0.0105, 0.9787, -0.052, 0.1983],
			"scale": [1.0, 1.0, 1.0, 1.0, 1.0, 1.0]
		},
		{
			"position": [0.0, 0.0, -0.0, 1.1943, -0.3749, -3.2106],
			"quaternion": [0.0, 0.0, -0.0, 1.0, 0.0096, 0.9827, -0.0536, 0.1769],
			"scale": [1.0, 1.0, 1.0, 1.0, 1.0, 1.0]
		},
		{
			"position": [0.0, 0.0, -0.0, 1.0525, -0.3846, -3.2587],
			"quaternion": [0.0, 0.0, -0.0, 1.0, 0.0087, 0.9863, -0.0552, 0.1553],
			"scale": [1.0, 1.0, 1.0, 1.0, 1.0, 1.0]
		},
		{
			"position": [0.0, 0.0, -0.0, 0.9088, -0.3944, -3.3005],
			"quaternion": [0.0, 0.0, -0.0, 1.0, 0.0077, 0.9894, -0.0568, 0.1337],
			"scale": [1.0, 1.0, 1.0, 1.0, 1.0, 1.0]
		},
		{
			"position": [0.0, 0.0, -0.0, 0.7635, -0.4041, -3.336],
			"quaternion": [0.0, 0.0, -0.0, 1.0, 0.0066, 0.992, -0.0584, 0.1121],
			"scale": [1.0, 1.0, 1.0, 1.0, 1.0, 1.0]
		},
		{
			"position": [0.0, 0.0, -0.0, 0.6167, -0.4139, -3.365],
			"quaternion": [0.0, 0.0, -0.0, 1.0, 0.0054, 0.9941, -0.0599, 0.0903],
			"scale": [1.0, 1.0, 1.0, 1.0, 1.0, 1.0]
		},
		{
			"position": [0.0, 0.0, -0.0, 0.4689, -0.4237, -3.3876],
			"quaternion": [0.0, 0.0, -0.0, 1.0, 0.0042, 0.9957, -0.0614, 0.0686],
			"scale": [1.0, 1.0, 1.0, 1.0, 1.0, 1.0]
		},
		{
			"position": [0.0, 0.0, -0.0, 0.3203, -0.4335, -3.4036],
			"quaternion": [0.0, 0.0, -0.0, 1.0, 0.003, 0.9969, -0.0629, 0.0468],
			"scale": [1.0, 1.0, 1.0, 1.0, 1.0, 1.0]
		},
		{
			"position": [0.0, 0.0, -0.0, 0.1713, -0.4432, -3.4131],
			"quaternion": [0.0, 0.0, -0.0, 1.0, 0.0016, 0.9976, -0.0644, 0.025],
			"scale": [1.0, 1.0, 1.0, 1.0, 1.0, 1.0]
		},
		{
			"position": [0.0, 0.0, -0.0, 0.0219, -0.453, -3.416],
			"quaternion": [0.0, 0.0, -0.0, 1.0, 0.0002, 0.9978, -0.0659, 0.0032],
			"scale": [1.0, 1.0, 1.0, 1.0, 1.0, 1.0]
		},
		{
			"position": [0.0, 0.0, -0.0, -0.1273, -0.4628, -3.4124],
			"quaternion": [0.0, 0.0, -0.0, 1.0, -0.0013, 0.9976, -0.0673, -0.0186],
			"scale": [1.0, 1.0, 1.0, 1.0, 1.0, 1.0]
		},
		{
			"position": [0.0, 0.0, -0.0, -0.2762, -0.4726, -3.4023],
			"quaternion": [0.0, 0.0, -0.0, 1.0, -0.0028, 0.9968, -0.0687, -0.0404],
			"scale": [1.0, 1.0, 1.0, 1.0, 1.0, 1.0]
		},
		{
			"position": [0.0, 0.0, -0.0, -0.4244, -0.4824, -3.3856],
			"quaternion": [0.0, 0.0, -0.0, 1.0, -0.0044, 0.9956, -0.07, -0.0622],
			"scale": [1.0, 1.0, 1.0, 1.0, 1.0, 1.0]
		},
		{
			"position": [0.0, 0.0, -0.0, -0.5717, -0.4922, -3.3624],
			"quaternion": [0.0, 0.0, -0.0, 1.0, -0.006, 0.9939, -0.0713, -0.0839],
			"scale": [1.0, 1.0, 1.0, 1.0, 1.0, 1.0]
		},
		{
			"position": [0.0, 0.0, -0.0, -0.7178, -0.502, -3.3328],
			"quaternion": [0.0, 0.0, -0.0, 1.0, -0.0077, 0.9917, -0.0726, -0.1056],
			"scale": [1.0, 1.0, 1.0, 1.0, 1.0, 1.0]
		},
		{
			"position": [0.0, 0.0, -0.0, -0.8624, -0.5118, -3.2969],
			"quaternion": [0.0, 0.0, -0.0, 1.0, -0.0095, 0.9891, -0.0739, -0.1272],
			"scale": [1.0, 1.0, 1.0, 1.0, 1.0, 1.0]
		},
		{
			"position": [0.0, 0.0, -0.0, -1.0052, -0.5217, -3.2546],
			"quaternion": [0.0, 0.0, -0.0, 1.0, -0.0113, 0.986, -0.0751, -0.1488],
			"scale": [1.0, 1.0, 1.0, 1.0, 1.0, 1.0]
		},
		{
			"position": [0.0, 0.0, -0.0, -1.1459, -0.5315, -3.2061],
			"quaternion": [0.0, 0.0, -0.0, 1.0, -0.0132, 0.9824, -0.0762, -0.1703],
			"scale": [1.0, 1.0, 1.0, 1.0, 1.0, 1.0]
		},
		{
			"position": [0.0, 0.0, -0.0, -1.2844, -0.5414, -3.1516],
			"quaternion": [0.0, 0.0, -0.0, 1.0, -0.0152, 0.9783, -0.0773, -0.1917],
			"scale": [1.0, 1.0, 1.0, 1.0, 1.0, 1.0]
		},
		{
			"position": [0.0, 0.0, -0.0, -1.4202, -0.5513, -3.091],
			"quaternion": [0.0, 0.0, -0.0, 1.0, -0.0171, 0.9738, -0.0784, -0.213],
			"scale": [1.0, 1.0, 1.0, 1.0, 1.0, 1.0]
		},
		{
			"position": [0.0, 0.0, -0.0, -1.5532, -0.5612, -3.0245],
			"quaternion": [0.0, 0.0, -0.0, 1.0, -0.0192, 0.9687, -0.0794, -0.2342],
			"scale": [1.0, 1.0, 1.0, 1.0, 1.0, 1.0]
		},
		{
			"position": [0.0, 0.0, -0.0, -1.683, -0.5711, -2.9523],
			"quaternion": [0.0, 0.0, -0.0, 1.0, -0.0213, 0.9633, -0.0804, -0.2553],
			"scale": [1.0, 1.0, 1.0, 1.0, 1.0, 1.0]
		},
		{
			"position": [0.0, 0.0, -0.0, -1.8095, -0.581, -2.8745],
			"quaternion": [0.0, 0.0, -0.0, 1.0, -0.0235, 0.9574, -0.0813, -0.2762],
			"scale": [1.0, 1.0, 1.0, 1.0, 1.0, 1.0]
		},
		{
			"position": [0.0, 0.0, -0.0, -1.9324, -0.5909, -2.7913],
			"quaternion": [0.0, 0.0, -0.0, 1.0, -0.0257, 0.951, -0.0821, -0.2971],
			"scale": [1.0, 1.0, 1.0, 1.0, 1.0, 1.0]
		},
		{
			"position": [0.0, 0.0, -0.0, -2.0515, -0.6009, -2.7028],
			"quaternion": [0.0, 0.0, -0.0, 1.0, -0.0279, 0.9441, -0.083, -0.3177],
			"scale": [1.0, 1.0, 1.0, 1.0, 1.0, 1.0]
		},
		{
			"position": [0.0, 0.0, -0.0, -2.1665, -0.6109, -2.6092],
			"quaternion": [0.0, 0.0, -0.0, 1.0, -0.0302, 0.9368, -0.0837, -0.3382],
			"scale": [1.0, 1.0, 1.0, 1.0, 1.0, 1.0]
		},
		{
			"position": [0.0, 0.0, -0.0, -2.2773, -0.6209, -2.5107],
			"quaternion": [0.0, 0.0, -0.0, 1.0, -0.0326, 0.9291, -0.0844, -0.3586],
			"scale": [1.0, 1.0, 1.0, 1.0, 1.0, 1.0]
		},
		{
			"position": [0.0, 0.0, -0.0, -2.3835, -0.6309, -2.4075],
			"quaternion": [0.0, 0.0, -0.0, 1.0, -0.035, 0.9209, -0.085, -0.3788],
			"scale": [1.0, 1.0, 1.0, 1.0, 1.0, 1.0]
		},
		{
			"position": [0.0, 0.0, -0.0, -2.485, -0.6409, -2.2997],
			"quaternion": [0.0, 0.0, -0.0, 1.0, -0.0374, 0.9123, -0.0856, -0.3987],
			"scale": [1.0, 1.0, 1.0, 1.0, 1.0, 1.0]
		},
		{
			"position": [0.0, 0.0, -0.0, -2.5817, -0.651, -2.1877],
			"quaternion": [0.0, 0.0, -0.0, 1.0, -0.0399, 0.9032, -0.0861, -0.4185],
			"scale": [1.0, 1.0, 1.0, 1.0, 1.0, 1.0]
		},
		{
			"position": [0.0, 0.0, -0.0, -2.6733, -0.6611, -2.0716],
			"quaternion": [0.0, 0.0, -0.0, 1.0, -0.0424, 0.8937, -0.0865, -0.4381],
			"scale": [1.0, 1.0, 1.0, 1.0, 1.0, 1.0]
		},
		{
			"position": [0.0, 0.0, -0.0, -2.7596, -0.6712, -1.9517],
			"quaternion": [0.0, 0.0, -0.0, 1.0, -0.045, 0.8838, -0.0869, -0.4575],
			"scale": [1.0, 1.0, 1.0, 1.0, 1.0, 1.0]
		},
		{
			"position": [0.0, 0.0, -0.0, -2.8406, -0.6813, -1.8281],
			"quaternion": [0.0, 0.0, -0.0, 1.0, -0.0476, 0.8735, -0.0872, -0.4766],
			"scale": [1.0, 1.0, 1.0, 1.0, 1.0, 1.0]
		},
		{
			"position": [0.0, 0.0, -0.0, -2.9159, -0.6915, -1.7012],
			"quaternion": [0.0, 0.0, -0.0, 1.0, -0.0502, 0.8627, -0.0875, -0.4955],
			"scale": [1.0, 1.0, 1.0, 1.0, 1.0, 1.0]
		},
		{
			"position": [0.0, 0.0, -0.0, -2.9856, -0.7017, -1.5712],
			"quaternion": [0.0, 0.0, -0.0, 1.0, -0.0529, 0.8516, -0.0876, -0.5142],
			"scale": [1.0, 1.0, 1.0, 1.0, 1.0, 1.0]
		},
		{
			"position": [0.0, 0.0, -0.0, -3.0495, -0.7119, -1.4383],
			"quaternion": [0.0, 0.0, -0.0, 1.0, -0.0556, 0.84, -0.0877, -0.5326],
			"scale": [1.0, 1.0, 1.0, 1.0, 1.0, 1.0]
		},
		{
			"position": [0.0, 0.0, -0.0, -3.1074, -0.7222, -1.3028],
			"quaternion": [0.0, 0.0, -0.0, 1.0, -0.0584, 0.828, -0.0877, -0.5507],
			"scale": [1.0, 1.0, 1.0, 1.0, 1.0, 1.0]
		},
		{
			"position": [0.0, 0.0, -0.0, -3.1593, -0.7324, -1.165],
			"quaternion": [0.0, 0.0, -0.0, 1.0, -0.0611, 0.8157, -0.0877, -0.5686],
			"scale": [1.0, 1.0, 1.0, 1.0, 1.0, 1.0]
		},
		{
			"position": [0.0, 0.0, -0.0, -3.2051, -0.7427, -1.0252],
			"quaternion": [0.0, 0.0, -0.0, 1.0, -0.0639, 0.8029, -0.0876, -0.5862],
			"scale": [1.0, 1.0, 1.0, 1.0, 1.0, 1.0]
		},
		{
			"position": [0.0, 0.0, -0.0, -3.2446, -0.7531, -0.8835],
			"quaternion": [0.0, 0.0, -0.0, 1.0, -0.0667, 0.7898, -0.0874, -0.6035],
			"scale": [1.0, 1.0, 1.0, 1.0, 1.0, 1.0]
		},
		{
			"position": [0.0, 0.0, -0.0, -3.2778, -0.7634, -0.7404],
			"quaternion": [0.0, 0.0, -0.0, 1.0, -0.0696, 0.7763, -0.0871, -0.6205],
			"scale": [1.0, 1.0, 1.0, 1.0, 1.0, 1.0]
		},
		{
			"position": [0.0, 0.0, -0.0, -3.3047, -0.7738, -0.596],
			"quaternion": [0.0, 0.0, -0.0, 1.0, -0.0725, 0.7624, -0.0867, -0.6372],
			"scale": [1.0, 1.0, 1.0, 1.0, 1.0, 1.0]
		},
		{
			"position": [0.0, 0.0, -0.0, -3.3252, -0.7843, -0.4507],
			"quaternion": [0.0, 0.0, -0.0, 1.0, -0.0754, 0.7481, -0.0863, -0.6536],
			"scale": [1.0, 1.0, 1.0, 1.0, 1.0, 1.0]
		},
		{
			"position": [0.0, 0.0, -0.0, -3.3392, -0.7947, -0.3048],
			"quaternion": [0.0, 0.0, -0.0, 1.0, -0.0783, 0.7335, -0.0857, -0.6696],
			"scale": [1.0, 1.0, 1.0, 1.0, 1.0, 1.0]
		},
		{
			"position": [0.0, 0.0, -0.0, -3.3469, -0.8052, -0.1584],
			"quaternion": [0.0, 0.0, -0.0, 1.0, -0.0812, 0.7186, -0.0851, -0.6854],
			"scale": [1.0, 1.0, 1.0, 1.0, 1.0, 1.0]
		},
		{
			"position": [0.0, 0.0, -0.0, -3.348, -0.8158, -0.012],
			"quaternion": [0.0, 0.0, -0.0, 1.0, -0.0841, 0.7033, -0.0845, -0.7008],
			"scale": [1.0, 1.0, 1.0, 1.0, 1.0, 1.0]
		},
		{
			"position": [0.0, 0.0, -0.0, -3.3428, -0.8264, 0.1342],
			"quaternion": [0.0, 0.0, -0.0, 1.0, -0.0871, 0.6877, -0.0837, -0.7159],
			"scale": [1.0, 1.0, 1.0, 1.0, 1.0, 1.0]
		},
		{
			"position": [0.0, 0.0, -0.0, -3.3311, -0.837, 0.2799],
			"quaternion": [0.0, 0.0, -0.0, 1.0, -0.0901, 0.6718, -0.0828, -0.7306],
			"scale": [1.0, 1.0, 1.0, 1.0, 1.0, 1.0]
		},
		{
			"position": [0.0, 0.0, -0.0, -3.313, -0.8476, 0.4249],
			"quaternion": [0.0, 0.0, -0.0, 1.0, -0.093, 0.6555, -0.0819, -0.7449],
			"scale": [1.0, 1.0, 1.0, 1.0, 1.0, 1.0]
		},
		{
			"position": [0.0, 0.0, -0.0, -3.2886, -0.8583, 0.5688],
			"quaternion": [0.0, 0.0, -0.0, 1.0, -0.096, 0.6389, -0.0808, -0.7589],
			"scale": [1.0, 1.0, 1.0, 1.0, 1.0, 1.0]
		},
		{
			"position": [0.0, 0.0, -0.0, -3.2579, -0.869, 0.7113],
			"quaternion": [0.0, 0.0, -0.0, 1.0, -0.099, 0.6221, -0.0797, -0.7726],
			"scale": [1.0, 1.0, 1.0, 1.0, 1.0, 1.0]
		},
		{
			"position": [0.0, 0.0, -0.0, -3.221, -0.8798, 0.8523],
			"quaternion": [0.0, 0.0, -0.0, 1.0, -0.102, 0.6049, -0.0785, -0.7858],
			"scale": [1.0, 1.0, 1.0, 1.0, 1.0, 1.0]
		},
		{
			"position": [0.0, 0.0, -0.0, -3.1779, -0.8906, 0.9914],
			"quaternion": [0.0, 0.0, -0.0, 1.0, -0.105, 0.5875, -0.0772, -0.7987],
			"scale": [1.0, 1.0, 1.0, 1.0, 1.0, 1.0]
		},
		{
			"position": [0.0, 0.0, -0.0, -3.1288, -0.9015, 1.1283],
			"quaternion": [0.0, 0.0, -0.0, 1.0, -0.108, 0.5698, -0.0758, -0.8111],
			"scale": [1.0, 1.0, 1.0, 1.0, 1.0, 1.0]
		},
		{
			"position": [0.0, 0.0, -0.0, -3.0737, -0.9124, 1.2628],
			"quaternion": [0.0, 0.0, -0.0, 1.0, -0.111, 0.5518, -0.0744, -0.8232],
			"scale": [1.0, 1.0, 1.0, 1.0, 1.0, 1.0]
		},
		{
			"position": [0.0, 0.0, -0.0, -3.0129, -0.9233, 1.3946],
			"quaternion": [0.0, 0.0, -0.0, 1.0, -0.1139, 0.5335, -0.0728, -0.8349],
			"scale": [1.0, 1.0, 1.0, 1.0, 1.0, 1.0]
		},
		{
			"position": [0.0, 0.0, -0.0, -2.9463, -0.9343, 1.5236],
			"quaternion": [0.0, 0.0, -0.0, 1.0, -0.1169, 0.515, -0.0712, -0.8462],
			"scale": [1.0, 1.0, 1.0, 1.0, 1.0, 1.0]
		},
		{
			"position": [0.0, 0.0, -0.0, -2.8742, -0.9453, 1.6493],
			"quaternion": [0.0, 0.0, -0.0, 1.0, -0.1198, 0.4963, -0.0694, -0.857],
			"scale": [1.0, 1.0, 1.0, 1.0, 1.0, 1.0]
		},
		{
			"position": [0.0, 0.0, -0.0, -2.7967, -0.9564, 1.7716],
			"quaternion": [0.0, 0.0, -0.0, 1.0, -0.1228, 0.4774, -0.0676, -0.8675],
			"scale": [1.0, 1.0, 1.0, 1.0, 1.0, 1.0]
		},
		{
			"position": [0.0, 0.0, -0.0, -2.714, -0.9675, 1.8903],
			"quaternion": [0.0, 0.0, -0.0, 1.0, -0.1257, 0.4582, -0.0656, -0.8775],
			"scale": [1.0, 1.0, 1.0, 1.0, 1.0, 1.0]
		},
		{
			"position": [0.0, 0.0, -0.0, -2.6262, -0.9787, 2.0051],
			"quaternion": [0.0, 0.0, -0.0, 1.0, -0.1286, 0.4388, -0.0636, -0.8871],
			"scale": [1.0, 1.0, 1.0, 1.0, 1.0, 1.0]
		},
		{
			"position": [0.0, 0.0, -0.0, -2.5335, -0.9899, 2.1158],
			"quaternion": [0.0, 0.0, -0.0, 1.0, -0.1315, 0.4192, -0.0615, -0.8962],
			"scale": [1.0, 1.0, 1.0, 1.0, 1.0, 1.0]
		},
		{
			"position": [0.0, 0.0, -0.0, -2.4361, -1.0011, 2.2222],
			"quaternion": [0.0, 0.0, -0.0, 1.0, -0.1343, 0.3994, -0.0593, -0.9049],
			"scale": [1.0, 1.0, 1.0, 1.0, 1.0, 1.0]
		},
		{
			"position": [0.0, 0.0, -0.0, -2.3342, -1.0124, 2.3241],
			"quaternion": [0.0, 0.0, -0.0, 1.0, -0.1372, 0.3794, -0.057, -0.9132],
			"scale": [1.0, 1.0, 1.0, 1.0, 1.0, 1.0]
		},
		{
			"position": [0.0, 0.0, -0.0, -2.2281, -1.0238, 2.4213],
			"quaternion": [0.0, 0.0, -0.0, 1.0, -0.14, 0.3593, -0.0546, -0.9211],
			"scale": [1.0, 1.0, 1.0, 1.0, 1.0, 1.0]
		},
		{
			"position": [0.0, 0.0, -0.0, -2.1178, -1.0352, 2.5136],
			"quaternion": [0.0, 0.0, -0.0, 1.0, -0.1427, 0.339, -0.0521, -0.9284],
			"scale": [1.0, 1.0, 1.0, 1.0, 1.0, 1.0]
		},
		{
			"position": [0.0, 0.0, -0.0, -2.0038, -1.0466, 2.6009],
			"quaternion": [0.0, 0.0, -0.0, 1.0, -0.1455, 0.3185, -0.0495, -0.9354],
			"scale": [1.0, 1.0, 1.0, 1.0, 1.0, 1.0]
		},
		{
			"position": [0.0, 0.0, -0.0, -1.8861, -1.0581, 2.6829],
			"quaternion": [0.0, 0.0, -0.0, 1.0, -0.1482, 0.2979, -0.0469, -0.9419],
			"scale": [1.0, 1.0, 1.0, 1.0, 1.0, 1.0]
		},
		{
			"position": [0.0, 0.0, -0.0, -1.765, -1.0697, 2.7596],
			"quaternion": [0.0, 0.0, -0.0, 1.0, -0.1508, 0.2772, -0.0441, -0.9479],
			"scale": [1.0, 1.0, 1.0, 1.0, 1.0, 1.0]
		},
		{
			"position": [0.0, 0.0, -0.0, -1.6408, -1.0813, 2.8308],
			"quaternion": [0.0, 0.0, -0.0, 1.0, -0.1535, 0.2563, -0.0413, -0.9534],
			"scale": [1.0, 1.0, 1.0, 1.0, 1.0, 1.0]
		},
		{
			"position": [0.0, 0.0, -0.0, -1.5137, -1.093, 2.8964],
			"quaternion": [0.0, 0.0, -0.0, 1.0, -0.156, 0.2354, -0.0383, -0.9585],
			"scale": [1.0, 1.0, 1.0, 1.0, 1.0, 1.0]
		},
		{
			"position": [0.0, 0.0, -0.0, -1.3841, -1.1047, 2.9562],
			"quaternion": [0.0, 0.0, -0.0, 1.0, -0.1586, 0.2143, -0.0353, -0.9632],
			"scale": [1.0, 1.0, 1.0, 1.0, 1.0, 1.0]
		},
		{
			"position": [0.0, 0.0, -0.0, -1.252, -1.1165, 3.0101],
			"quaternion": [0.0, 0.0, -0.0, 1.0, -0.161, 0.1932, -0.0322, -0.9673],
			"scale": [1.0, 1.0, 1.0, 1.0, 1.0, 1.0]
		},
		{
			"position": [0.0, 0.0, -0.0, -1.1179, -1.1283, 3.0581],
			"quaternion": [0.0, 0.0, -0.0, 1.0, -0.1635, 0.1719, -0.0289, -0.971],
			"scale": [1.0, 1.0, 1.0, 1.0, 1.0, 1.0]
		},
		{
			"position": [0.0, 0.0, -0.0, -0.9819, -1.1402, 3.1001],
			"quaternion": [0.0, 0.0, -0.0, 1.0, -0.1658, 0.1506, -0.0256, -0.9742],
			"scale": [1.0, 1.0, 1.0, 1.0, 1.0, 1.0]
		},
		{
			"position": [0.0, 0.0, -0.0, -0.8444, -1.1521, 3.136],
			"quaternion": [0.0, 0.0, -0.0, 1.0, -0.1682, 0.1292, -0.0222, -0.977],
			"scale": [1.0, 1.0, 1.0, 1.0, 1.0, 1.0]
		},
		{
			"position": [0.0, 0.0, -0.0, -0.7057, -1.1641, 3.1657],
			"quaternion": [0.0, 0.0, -0.0, 1.0, -0.1704, 0.1078, -0.0188, -0.9793],
			"scale": [1.0, 1.0, 1.0, 1.0, 1.0, 1.0]
		},
		{
			"position": [0.0, 0.0, -0.0, -0.5659, -1.1761, 3.1893],
			"quaternion": [0.0, 0.0, -0.0, 1.0, -0.1726, 0.0864, -0.0152, -0.9811],
			"scale": [1.0, 1.0, 1.0, 1.0, 1.0, 1.0]
		},
		{
			"position": [0.0, 0.0, -0.0, -0.4254, -1.1883, 3.2066],
			"quaternion": [0.0, 0.0, -0.0, 1.0, -0.1747, 0.0649, -0.0115, -0.9824],
			"scale": [1.0, 1.0, 1.0, 1.0, 1.0, 1.0]
		},
		{
			"position": [0.0, 0.0, -0.0, -0.2845, -1.2004, 3.2176],
			"quaternion": [0.0, 0.0, -0.0, 1.0, -0.1768, 0.0434, -0.0078, -0.9833],
			"scale": [1.0, 1.0, 1.0, 1.0, 1.0, 1.0]
		},
		{
			"position": [0.0, 0.0, -0.0, -0.1434, -1.2126, 3.2224],
			"quaternion": [0.0, 0.0, -0.0, 1.0, -0.1788, 0.0219, -0.004, -0.9836],
			"scale": [1.0, 1.0, 1.0, 1.0, 1.0, 1.0]
		},
		{
			"position": [0.0, 0.0, -0.0, -0.0025, -1.2249, 3.221],
			"quaternion": [0.0, 0.0, -0.0, 1.0, -0.1807, 0.0004, -0.0001, -0.9835],
			"scale": [1.0, 1.0, 1.0, 1.0, 1.0, 1.0]
		},
		{
			"position": [0.0, 0.0, -0.0, 0.1381, -1.2373, 3.2133],
			"quaternion": [0.0, 0.0, -0.0, 1.0, -0.1825, -0.0211, 0.0039, -0.983],
			"scale": [1.0, 1.0, 1.0, 1.0, 1.0, 1.0]
		},
		{
			"position": [0.0, 0.0, -0.0, 0.278, -1.2496, 3.1994],
			"quaternion": [0.0, 0.0, -0.0, 1.0, -0.1843, -0.0426, 0.008, -0.9819],
			"scale": [1.0, 1.0, 1.0, 1.0, 1.0, 1.0]
		},
		{
			"position": [0.0, 0.0, -0.0, 0.4169, -1.2621, 3.1794],
			"quaternion": [0.0, 0.0, -0.0, 1.0, -0.186, -0.064, 0.0121, -0.9804],
			"scale": [1.0, 1.0, 1.0, 1.0, 1.0, 1.0]
		},
		{
			"position": [0.0, 0.0, -0.0, 0.5545, -1.2746, 3.1532],
			"quaternion": [0.0, 0.0, -0.0, 1.0, -0.1876, -0.0854, 0.0164, -0.9784],
			"scale": [1.0, 1.0, 1.0, 1.0, 1.0, 1.0]
		},
		{
			"position": [0.0, 0.0, -0.0, 0.6907, -1.2872, 3.1211],
			"quaternion": [0.0, 0.0, -0.0, 1.0, -0.1891, -0.1067, 0.0207, -0.9759],
			"scale": [1.0, 1.0, 1.0, 1.0, 1.0, 1.0]
		},
		{
			"position": [0.0, 0.0, -0.0, 0.8251, -1.2998, 3.083],
			"quaternion": [0.0, 0.0, -0.0, 1.0, -0.1905, -0.128, 0.0251, -0.973],
			"scale": [1.0, 1.0, 1.0, 1.0, 1.0, 1.0]
		},
		{
			"position": [0.0, 0.0, -0.0, 0.9575, -1.3125, 3.039],
			"quaternion": [0.0, 0.0, -0.0, 1.0, -0.1919, -0.1491, 0.0295, -0.9696],
			"scale": [1.0, 1.0, 1.0, 1.0, 1.0, 1.0]
		},
		{
			"position": [0.0, 0.0, -0.0, 1.0876, -1.3253, 2.9893],
			"quaternion": [0.0, 0.0, -0.0, 1.0, -0.1931, -0.1702, 0.034, -0.9657],
			"scale": [1.0, 1.0, 1.0, 1.0, 1.0, 1.0]
		},
		{
			"position": [0.0, 0.0, -0.0, 1.2151, -1.3381, 2.9339],
			"quaternion": [0.0, 0.0, -0.0, 1.0, -0.1943, -0.1912, 0.0386, -0.9614],
			"scale": [1.0, 1.0, 1.0, 1.0, 1.0, 1.0]
		},
		{
			"position": [0.0, 0.0, -0.0, 1.3398, -1.351, 2.8731],
			"quaternion": [0.0, 0.0, -0.0, 1.0, -0.1953, -0.2121, 0.0433, -0.9566],
			"scale": [1.0, 1.0, 1.0, 1.0, 1.0, 1.0]
		},
		{
			"position": [0.0, 0.0, -0.0, 1.4615, -1.364, 2.8069],
			"quaternion": [0.0, 0.0, -0.0, 1.0, -0.1963, -0.2328, 0.048, -0.9513],
			"scale": [1.0, 1.0, 1.0, 1.0, 1.0, 1.0]
		},
		{
			"position": [0.0, 0.0, -0.0, 1.58, -1.377, 2.7354],
			"quaternion": [0.0, 0.0, -0.0, 1.0, -0.1971, -0.2535, 0.0528, -0.9456],
			"scale": [1.0, 1.0, 1.0, 1.0, 1.0, 1.0]
		},
		{
			"position": [0.0, 0.0, -0.0, 1.6949, -1.39, 2.659],
			"quaternion": [0.0, 0.0, -0.0, 1.0, -0.1979, -0.2739, 0.0577, -0.9394],
			"scale": [1.0, 1.0, 1.0, 1.0, 1.0, 1.0]
		},
		{
			"position": [0.0, 0.0, -0.0, 1.8061, -1.4032, 2.5776],
			"quaternion": [0.0, 0.0, -0.0, 1.0, -0.1985, -0.2943, 0.0626, -0.9328],
			"scale": [1.0, 1.0, 1.0, 1.0, 1.0, 1.0]
		},
		{
			"position": [0.0, 0.0, -0.0, 1.9134, -1.4164, 2.4915],
			"quaternion": [0.0, 0.0, -0.0, 1.0, -0.199, -0.3144, 0.0676, -0.9257],
			"scale": [1.0, 1.0, 1.0, 1.0, 1.0, 1.0]
		},
		{
			"position": [0.0, 0.0, -0.0, 2.0166, -1.4296, 2.4009],
			"quaternion": [0.0, 0.0, -0.0, 1.0, -0.1995, -0.3345, 0.0726, -0.9182],
			"scale": [1.0, 1.0, 1.0, 1.0, 1.0, 1.0]
		},
		{
			"position": [0.0, 0.0, -0.0, 2.1155, -1.443, 2.306],
			"quaternion": [0.0, 0.0, -0.0, 1.0, -0.1998, -0.3543, 0.0777, -0.9102],
			"scale": [1.0, 1.0, 1.0, 1.0, 1.0, 1.0]
		},
		{
			"position": [0.0, 0.0, -0.0, 2.2098, -1.4563, 2.207],
			"quaternion": [0.0, 0.0, -0.0, 1.0, -0.1999, -0.3739, 0.0829, -0.9019],
			"scale": [1.0, 1.0, 1.0, 1.0, 1.0, 1.0]
		}
	]
}
